{
  "-1.0356438,51.3720595": {
    "name": "Mortimer",
    "rating": "highlight"
  },
  "-1.0608367,51.3299792": {
    "name": "Bramley",
    "rating": "verified"
  },
  "0.3061936,51.2931422": {
    "name": "Borough Green & Wrotham",
    "rating": "verified"
  },
  "0.1819438,51.2764117": {
    "name": "Sevenoaks",
    "rating": "highlight"
  },
  "-0.6224578,51.800672": {
    "name": "Tring",
    "rating": "highlight"
  },
  "-0.4422487,51.2192418": {
    "name": "Gomshall",
    "rating": "highlight"
  },
  "-1.3726319,51.8247081": {
    "name": "Hanborough",
    "rating": "highlight"
  },
  "0.0113494,50.8705975": {
    "name": "Lewes",
    "rating": "highlight"
  },
  "0.0306729,50.83111": {
    "name": "Southease",
    "rating": "verified"
  },
  "-0.5419326,50.8966534": {
    "name": "Amberley",
    "rating": "highlight"
  },
  "-0.5462656,50.8480121": {
    "name": "Arundel",
    "rating": "verified"
  },
  "0.2815355,50.7696435": {
    "name": "Eastbourne",
    "rating": "highlight"
  },
  "0.1000064,50.7729203": {
    "name": "Seaford",
    "rating": "verified"
  },
  "0.3253781,50.8157704": {
    "name": "Pevensey and Westham",
    "rating": "verified"
  },
  "0.4949233,50.9128867": {
    "name": "Battle",
    "rating": "highlight"
  },
  "-1.8064141,51.0705706": {
    "name": "Salisbury",
    "rating": "highlight"
  },
  "-0.3276687,51.7504966": {
    "name": "St Albans City",
    "rating": "verified"
  },
  "-0.7476905,51.7618168": {
    "name": "Wendover",
    "rating": "verified"
  },
  "0.1967655,52.2622818": {
    "name": "Waterbeach",
    "rating": "verified"
  },
  "0.2664989,52.3906885": {
    "name": "Ely",
    "rating": "verified"
  },
  "0.2630275,51.1300963": {
    "name": "Tunbridge Wells",
    "rating": "verified"
  },
  "1.1537821,51.0847184": {
    "name": "Folkestone West",
    "rating": "verified"
  },
  "-0.137032,51.0555957": {
    "name": "Balcombe",
    "rating": "verified"
  },
  "-0.6326933,52.0212048": {
    "name": "Aspley Guise",
    "rating": "verified"
  },
  "0.7025193,50.9339128": {
    "name": "Winchelsea",
    "rating": "verified"
  },
  "0.5768255,50.8583028": {
    "name": "Hastings",
    "rating": "verified"
  },
  "0.1731809,51.1972733": {
    "name": "Penshurst",
    "rating": "verified"
  },
  "0.9760562,51.2444245": {
    "name": "Chilham",
    "rating": "verified"
  },
  "1.07582,51.274185": {
    "name": "Canterbury East",
    "rating": "verified"
  },
  "-1.1331195,51.5211885": {
    "name": "Goring & Streatley",
    "rating": "verified"
  },
  "-1.0904319,51.4853553": {
    "name": "Pangbourne",
    "rating": "verified"
  },
  "-0.899422,51.5338451": {
    "name": "Henley-on-Thames",
    "rating": "verified"
  },
  "-0.7664026,51.571086": {
    "name": "Marlow",
    "rating": "verified"
  },
  "-0.5811391,51.2372003": {
    "name": "Guildford",
    "rating": "verified"
  },
  "-0.1457168,50.9247179": {
    "name": "Hassocks",
    "rating": "verified"
  },
  "-0.8440858,51.7180454": {
    "name": "Princes Risborough",
    "rating": "verified"
  },
  "-0.6105638,51.4832744": {
    "name": "Windsor and Eton Central",
    "rating": "verified"
  },
  "-1.4457051,51.4026132": {
    "name": "Kintbury",
    "rating": "verified"
  },
  "0.1083284,51.3566115": {
    "name": "Chelsfield",
    "rating": "verified"
  },
  "0.1377154,52.1941089": {
    "name": "Cambridge",
    "rating": "verified"
  },
  "-0.3286723,51.2539871": {
    "name": "Box Hill & Westhumble",
    "rating": "verified"
  },
  "-0.8155144,50.8391034": {
    "name": "Fishbourne",
    "rating": "verified"
  },
  "-0.4331815,50.8176931": {
    "name": "Goring-by-Sea",
    "rating": "verified"
  },
  "-0.3761766,50.8186425": {
    "name": "Worthing",
    "rating": "verified"
  },
  "1.4052264,51.3410764": {
    "name": "Ramsgate",
    "rating": "verified"
  },
  "1.3719521,51.3851637": {
    "name": "Margate",
    "rating": "verified"
  },
  "0.009471,51.6325345": {
    "name": "Chingford",
    "rating": "verified"
  },
  "-1.7852844,51.5657001": {
    "name": "Swindon",
    "rating": "not-recommended"
  },
  "-0.134245,51.3220643": {
    "name": "Coulsdon Town",
    "rating": "not-recommended"
  },
  "-0.137974,51.315543": {
    "name": "Coulsdon South",
    "rating": "not-recommended"
  },
  "-1.5370862,50.7610847": {
    "name": "Lymington Town",
    "rating": "not-recommended"
  },
  "-0.6073643,51.6740875": {
    "name": "Amersham",
    "rating": "not-recommended"
  },
  "-0.165577,51.2400546": {
    "name": "Redhill",
    "rating": "not-recommended"
  },
  "-1.5734094,50.816746": {
    "name": "Brockenhurst",
    "rating": "not-recommended"
  },
  "0.215334,51.9798629": {
    "name": "Newport",
    "rating": "not-recommended"
  },
  "0.2071507,52.0044551": {
    "name": "Audley End",
    "rating": "not-recommended"
  },
  "-1.2425171,51.6112197": {
    "name": "Didcot Parkway",
    "rating": "not-recommended"
  },
  "-0.0178578,51.1264031": {
    "name": "East Grinstead",
    "rating": "verified"
  },
  "-1.628532,51.9024116": {
    "name": "Kingham",
    "rating": "verified"
  },
  "-2.0230749,51.6767954": {
    "name": "Kemble",
    "rating": "highlight"
  },
  "-2.1001222,51.8969882": {
    "name": "Cheltenham Spa",
    "rating": "verified"
  },
  "0.1033213,51.6717759": {
    "name": "Theydon Bois",
    "rating": "verified"
  },
  "-0.3241359,51.2411653": {
    "name": "Dorking",
    "rating": "unverified"
  },
  "-1.7002657,51.9921819": {
    "name": "Moreton-in-Marsh",
    "rating": "unverified"
  },
  "1.3048692,51.1259357": {
    "name": "Dover Priory",
    "rating": "unverified"
  },
  "-0.9071791,50.8481981": {
    "name": "Southbourne",
    "rating": "unverified"
  },
  "-0.781845,50.8318805": {
    "name": "Chichester",
    "rating": "unverified"
  },
  "-1.2599752,51.2541369": {
    "name": "Overton",
    "rating": "unverified"
  },
  "-0.8253668,51.6758974": {
    "name": "Saunderton",
    "rating": "unverified"
  },
  "0.4040202,52.7537968": {
    "name": "King's Lynn",
    "rating": "unverified"
  },
  "-1.6576697,50.7557623": {
    "name": "New Milton",
    "rating": "unverified"
  },
  "0.1971759,51.3129318": {
    "name": "Otford",
    "rating": "unverified"
  },
  "0.2112588,51.1939929": {
    "name": "Leigh",
    "rating": "unverified"
  },
  "0.4121616,51.2266654": {
    "name": "Yalding",
    "rating": "unverified"
  },
  "-0.5250129,51.2151195": {
    "name": "Chilworth",
    "rating": "unverified"
  },
  "-0.566879,51.2143603": {
    "name": "Shalford",
    "rating": "unverified"
  },
  "-0.6368939,51.163179": {
    "name": "Milford",
    "rating": "unverified"
  },
  "-0.7194871,51.0887757": {
    "name": "Haslemere",
    "rating": "unverified"
  },
  "-0.7924218,51.2118094": {
    "name": "Farnham",
    "rating": "unverified"
  },
  "-0.776776,51.3315657": {
    "name": "Blackwater",
    "rating": "unverified"
  },
  "-0.8681985,51.1812254": {
    "name": "Bentley",
    "rating": "unverified"
  },
  "0.1887766,51.3321241": {
    "name": "Shoreham",
    "rating": "unverified"
  },
  "0.2042149,51.3623288": {
    "name": "Eynsford",
    "rating": "unverified"
  },
  "0.2467483,50.8211277": {
    "name": "Polegate",
    "rating": "unverified"
  },
  "0.1657244,50.8404862": {
    "name": "Berwick",
    "rating": "unverified"
  },
  "0.0703481,50.8591176": {
    "name": "Glynde",
    "rating": "unverified"
  },
  "-0.2714448,50.8343756": {
    "name": "Shoreham-by-Sea",
    "rating": "unverified"
  },
  "-0.3232037,50.8270176": {
    "name": "Lancing",
    "rating": "unverified"
  },
  "-0.150065,51.2641687": {
    "name": "Merstham",
    "rating": "not-recommended"
  },
  "-0.2421857,51.308624": {
    "name": "Tattenham Corner",
    "rating": "verified"
  },
  "-0.0516667,51.2896975": {
    "name": "Woldingham",
    "rating": "unverified"
  },
  "0.3130406,51.0733883": {
    "name": "Wadhurst",
    "rating": "unverified"
  },
  "-0.3425203,51.4020159": {
    "name": "Hampton Court",
    "rating": "verified"
  },
  "-0.3004127,51.4632072": {
    "name": "Richmond",
    "rating": "verified"
  },
  "-0.284962,51.4771341": {
    "name": "Kew Gardens",
    "rating": "verified"
  },
  "-0.1653912,51.5552396": {
    "name": "Hampstead Heath",
    "rating": "verified"
  },
  "-0.1990432,51.4340563": {
    "name": "Wimbledon Park",
    "rating": "verified"
  },
  "1.3986457,51.2231068": {
    "name": "Deal",
    "rating": "unverified"
  },
  "1.3614558,51.3307843": {
    "name": "Thanet Parkway",
    "rating": "unverified"
  },
  "0.7468492,51.3889653": {
    "name": "Swale",
    "rating": "unverified"
  },
  "0.6110362,51.3666656": {
    "name": "Rainham",
    "rating": "unverified"
  },
  "0.7945675,51.531446": {
    "name": "Shoeburyness",
    "rating": "unverified"
  },
  "1.3498136,51.9670171": {
    "name": "Felixstowe",
    "rating": "unverified"
  },
  "1.3009038,51.3775024": {
    "name": "Birchington-on-Sea",
    "rating": "unverified"
  },
  "1.1183071,51.3644375": {
    "name": "Herne Bay",
    "rating": "unverified"
  },
  "-0.193118,51.6975545": {
    "name": "Potters Bar",
    "rating": "not-recommended"
  }
}
